setup.cfg
setup.py
descent/__init__.py
descent/algorithms.py
descent/main.py
descent/objectives.py
descent/proxops.py
descent/utils.py
descent.egg-info/PKG-INFO
descent.egg-info/SOURCES.txt
descent.egg-info/dependency_links.txt
descent.egg-info/requires.txt
descent.egg-info/top_level.txt