Metadata-Version: 1.1
Name: descent
Version: 0.2.5
Summary: First order optimization tools
Home-page: https://github.com/nirum/descent
Author: Niru Maheshwaranathan
Author-email: nirum@stanford.edu
License: MIT
Platform: UNKNOWN
Classifier: Development Status :: 4 - Beta
Classifier: Intended Audience :: Science/Research
Classifier: Operating System :: OS Independent
Classifier: Topic :: Scientific/Engineering
